dexsnake/__init__.py
dexsnake/uniswap_v2/__init__.py
dexsnake/uniswap_v2/config.py
dexsnake/uniswap_v2/factory.py
dexsnake/uniswap_v2/pair.py
dexsnake/uniswap_v2/router.py
dexsnake/uniswap_v2/abi/__init__.py
Dexsnake-0.0.1.dist-info/LICENSE
Dexsnake-0.0.1.dist-info/METADATA
Dexsnake-0.0.1.dist-info/WHEEL
Dexsnake-0.0.1.dist-info/top_level.txt
Dexsnake-0.0.1.dist-info/RECORD
