Metadata-Version: 2.1
Name: Dexsnake
Version: 0.0.1
Summary: A Python package for trading on decentralized exchanges like Uniswap.
Author-email: Leevi Kerkelä <leevi.kerkela@protonmail.com>
Project-URL: Homepage, https://github.com/kerkelae/dexsnake
Classifier: Programming Language :: Python :: 3
Classifier: License :: OSI Approved :: MIT License
Classifier: Operating System :: OS Independent
Requires-Python: >=3.8
License-File: LICENSE
Requires-Dist: web3
